fa2svg/__init__.py
fa2svg/_version.py
fa2svg/constants.py
fa2svg/converter.py
fa2svg-0.1.10.dist-info/LICENSE
fa2svg-0.1.10.dist-info/METADATA
fa2svg-0.1.10.dist-info/WHEEL
fa2svg-0.1.10.dist-info/top_level.txt
fa2svg-0.1.10.dist-info/RECORD
