Metadata-Version: 2.1
Name: fa2svg
Version: 0.1.10
Summary: Convert Font Awesome HTML tags into inline SVG
Home-page: https://github.com/meena-erian/fa2svg
Author: meena-erian
Project-URL: Source, https://github.com/meena-erian/fa2svg
Project-URL: Issue Tracker, https://github.com/meena-erian/fa2svg/issues
Requires-Python: >=3.6
License-File: LICENSE
Requires-Dist: beautifulsoup4
Requires-Dist: lxml
Requires-Dist: requests
Requires-Dist: cairosvg
